{
  "versao": 1,
  "geradoEm": null,
  "observacao": "Base semeada (RF-4). As séries 'correcao' (INPC até 08/2024, IPCA a partir de 09/2024) e 'taxaLegal' são preenchidas por scripts/seed-indices.mjs (IBGE/Bacen) antes da distribuição e completadas pela atualização automática do aplicativo (RNF-3). Vigências de salário mínimo conferidas com as fontes oficiais; valores futuros entram como 'estimado' até confirmação pela série SGS 1619 do Bacen.",
  "correcao": {},
  "taxaLegal": {},
  "salarioMinimo": [
    { "vigencia": "1999-05", "valor": 136.0, "status": "oficial", "fonte": "Lei nº 9.971/2000" },
    { "vigencia": "2000-04", "valor": 151.0, "status": "oficial", "fonte": "Lei nº 9.971/2000" },
    { "vigencia": "2001-04", "valor": 180.0, "status": "oficial", "fonte": "MP nº 2.142/2001" },
    { "vigencia": "2002-04", "valor": 200.0, "status": "oficial", "fonte": "Lei nº 10.525/2002" },
    { "vigencia": "2003-04", "valor": 240.0, "status": "oficial", "fonte": "Lei nº 10.699/2003" },
    { "vigencia": "2004-05", "valor": 260.0, "status": "oficial", "fonte": "Lei nº 10.888/2004" },
    { "vigencia": "2005-05", "valor": 300.0, "status": "oficial", "fonte": "Lei nº 11.164/2005" },
    { "vigencia": "2006-04", "valor": 350.0, "status": "oficial", "fonte": "Lei nº 11.321/2006" },
    { "vigencia": "2007-04", "valor": 380.0, "status": "oficial", "fonte": "Lei nº 11.498/2007" },
    { "vigencia": "2008-03", "valor": 415.0, "status": "oficial", "fonte": "Lei nº 11.709/2008" },
    { "vigencia": "2009-02", "valor": 465.0, "status": "oficial", "fonte": "Lei nº 11.944/2009" },
    { "vigencia": "2010-01", "valor": 510.0, "status": "oficial", "fonte": "Lei nº 12.255/2010" },
    { "vigencia": "2011-01", "valor": 540.0, "status": "oficial", "fonte": "Lei nº 12.382/2011" },
    { "vigencia": "2011-03", "valor": 545.0, "status": "oficial", "fonte": "Lei nº 12.382/2011" },
    { "vigencia": "2012-01", "valor": 622.0, "status": "oficial", "fonte": "Decreto nº 7.655/2011" },
    { "vigencia": "2013-01", "valor": 678.0, "status": "oficial", "fonte": "Decreto nº 7.872/2012" },
    { "vigencia": "2014-01", "valor": 724.0, "status": "oficial", "fonte": "Decreto nº 8.166/2013" },
    { "vigencia": "2015-01", "valor": 788.0, "status": "oficial", "fonte": "Decreto nº 8.381/2014" },
    { "vigencia": "2016-01", "valor": 880.0, "status": "oficial", "fonte": "Decreto nº 8.618/2015" },
    { "vigencia": "2017-01", "valor": 937.0, "status": "oficial", "fonte": "Decreto nº 8.948/2016" },
    { "vigencia": "2018-01", "valor": 954.0, "status": "oficial", "fonte": "Decreto nº 9.255/2017" },
    { "vigencia": "2019-01", "valor": 998.0, "status": "oficial", "fonte": "Decreto nº 9.661/2019" },
    { "vigencia": "2020-01", "valor": 1039.0, "status": "oficial", "fonte": "MP nº 916/2019" },
    { "vigencia": "2020-02", "valor": 1045.0, "status": "oficial", "fonte": "MP nº 919/2020" },
    { "vigencia": "2021-01", "valor": 1100.0, "status": "oficial", "fonte": "MP nº 1.021/2020" },
    { "vigencia": "2022-01", "valor": 1212.0, "status": "oficial", "fonte": "MP nº 1.091/2021" },
    { "vigencia": "2023-01", "valor": 1302.0, "status": "oficial", "fonte": "MP nº 1.143/2022" },
    { "vigencia": "2023-05", "valor": 1320.0, "status": "oficial", "fonte": "MP nº 1.172/2023" },
    { "vigencia": "2024-01", "valor": 1412.0, "status": "oficial", "fonte": "Decreto nº 11.864/2023" },
    { "vigencia": "2025-01", "valor": 1518.0, "status": "oficial", "fonte": "Decreto nº 12.342/2024" },
    { "vigencia": "2026-01", "valor": 1631.0, "status": "estimado", "fonte": "a confirmar (SGS 1619)" }
  ]
}
